<?xml version="1.0" encoding="UTF-8"?>
<!DOCTYPE hibernate-reverse-engineering PUBLIC "-//Hibernate/Hibernate Reverse Engineering DTD 3.0//EN" "http://hibernate.sourceforge.net/hibernate-reverse-engineering-3.0.dtd" >

<hibernate-reverse-engineering>
	<table name="paper_check" catalog="personnel_training">
		<primary-key>
			<generator class="native"></generator>
		</primary-key>
	</table>
	<table name="paper" catalog="personnel_training">
		<primary-key>
			<generator class="native"></generator>
		</primary-key>
	</table>
	<table name="post_graduate" catalog="personnel_training">
		<primary-key>
			<generator class="native"></generator>
		</primary-key>
	</table>
	<table name="project" catalog="personnel_training">
		<primary-key>
			<generator class="native"></generator>
		</primary-key>
	</table>
	<table name="send_paper" catalog="personnel_training">
		<primary-key>
			<generator class="native"></generator>
		</primary-key>
	</table>
	<table name="teacher" catalog="personnel_training">
		<primary-key>
			<generator class="native"></generator>
		</primary-key>
	</table>
	<table name="undergraduate" catalog="personnel_training">
		<primary-key>
			<generator class="native"></generator>
		</primary-key>
	</table>
<table name="user" catalog="personnel_training">
	<primary-key>
		<generator class="native"></generator>
	</primary-key>
</table>
</hibernate-reverse-engineering>